ubox_py_sdk/__init__.py
ubox_py_sdk/client.py
ubox_py_sdk/common_util.py
ubox_py_sdk/device.py
ubox_py_sdk/device_operations.py
ubox_py_sdk/exceptions.py
ubox_py_sdk/handler.py
ubox_py_sdk/jwt_util.py
ubox_py_sdk/logger.py
ubox_py_sdk/models.py
ubox_py_sdk/perf_data_example.json
ubox_py_sdk/perf_data_ios_example.json
ubox_py_sdk/perf_fields_explanation.md
ubox_py_sdk/perf_wrapper.py
ubox_py_sdk-0.1.42.dist-info/METADATA
ubox_py_sdk-0.1.42.dist-info/WHEEL
ubox_py_sdk-0.1.42.dist-info/RECORD
