Metadata-Version: 2.4
Name: ubox-py-sdk
Version: 0.1.42
Summary: 用于操作优测设备的python-sdk
Project-URL: Homepage, https://github.com/yourusername/ubox-py-sdk
Project-URL: Repository, https://github.com/yourusername/ubox-py-sdk
Project-URL: Documentation, https://ubox-py-sdk.readthedocs.io
Project-URL: Issues, https://github.com/yourusername/ubox-py-sdk/issues
Author-email: lainxxu <lainxxu@tencent.com>
Keywords: python,sdk,ubox,优测
Requires-Python: >=3.9.5
Requires-Dist: cryptography>=41.0.0
Requires-Dist: lxml>=6.0.0
Requires-Dist: pillow==11.3.0
Requires-Dist: pydantic>=2.0.0
Requires-Dist: pyjwt>=2.8.0
Requires-Dist: requests>=2.28.0
Provides-Extra: dev
Requires-Dist: black>=23.0.0; extra == 'dev'
Requires-Dist: flake8>=6.0.0; extra == 'dev'
Requires-Dist: isort>=5.12.0; extra == 'dev'
Requires-Dist: mypy>=1.0.0; extra == 'dev'
Provides-Extra: docs
Requires-Dist: sphinx-rtd-theme>=1.2.0; extra == 'docs'
Requires-Dist: sphinx>=6.0.0; extra == 'docs'
